foundrydb/__init__.py
foundrydb/__main__.py
foundrydb/catalog.py
foundrydb/cli.py
foundrydb/database.py
foundrydb/storage.py
foundrydb_core-0.1.0.dist-info/licenses/LICENSE
foundrydb_core-0.1.0.dist-info/METADATA
foundrydb_core-0.1.0.dist-info/WHEEL
foundrydb_core-0.1.0.dist-info/entry_points.txt
foundrydb_core-0.1.0.dist-info/top_level.txt
foundrydb_core-0.1.0.dist-info/RECORD
