Metadata-Version: 2.4
Name: foundrydb-core
Version: 0.1.0
Summary: A tiny educational SQL engine written in pure Python.
Home-page: https://github.com/a1inani/foundrydb
Author: Alinani Simukanga
License: MIT
Project-URL: Homepage, https://github.com/a1inani/foundrydb
Project-URL: Repository, https://github.com/a1inani/foundrydb
Project-URL: Issues, https://github.com/a1inani/foundrydb/issues
Classifier: Programming Language :: Python :: 3
Classifier: License :: OSI Approved :: MIT License
Classifier: Operating System :: OS Independent
Classifier: Topic :: Database :: Database Engines/Servers
Classifier: Intended Audience :: Education
Requires-Python: >=3.11
License-File: LICENSE
Provides-Extra: dev
Requires-Dist: pytest>=7.0; extra == "dev"
Requires-Dist: pytest-cov; extra == "dev"
Requires-Dist: ruff; extra == "dev"
Requires-Dist: mypy; extra == "dev"
Dynamic: home-page
Dynamic: license-file
Dynamic: requires-python
